<Properties StartupConfiguration="{41B687FE-CF52-4031-95B2-FC259BBBC43F}|Default">
  <MonoDevelop.Ide.ItemProperties.2022-08_220Treetop_220Tree_220House PreferredExecutionTarget="MonoDevelop.Default" />
  <MonoDevelop.Ide.Workbench ActiveDocument="Program.fs">
    <Files>
      <File FileName="Program.fs" Line="38" Column="1" />
    </Files>
    <Pads>
      <Pad Id="ProjectPad">
        <State name="__root__">
          <Node name="2022-08 Treetop Tree House" expanded="True">
            <Node name="2022-08 Treetop Tree House" expanded="True">
              <Node name="Program.fs" selected="True" />
            </Node>
          </Node>
        </State>
      </Pad>
    </Pads>
  </MonoDevelop.Ide.Workbench>
  <MonoDevelop.Ide.DebuggingService.PinnedWatches />
  <MonoDevelop.Ide.Workspace ActiveConfiguration="Debug" />
  <MonoDevelop.Ide.DebuggingService.Breakpoints>
    <BreakpointStore />
  </MonoDevelop.Ide.DebuggingService.Breakpoints>
  <MultiItemStartupConfigurations />
</Properties>